anything2image/__init__.py
anything2image/api.py
anything2image/app.py
anything2image/cli.py
anything2image/assets/depth/NYU0018.png
anything2image/assets/depth/NYU0794.png
anything2image/assets/depth/NYU0965.png
anything2image/assets/depth/NYU1406.png
anything2image/assets/depth/bird_depth.jpg
anything2image/assets/depth/car_depth.jpg
anything2image/assets/depth/dog_depth.jpg
anything2image/assets/image/bird.png
anything2image/assets/image/bird_image.jpg
anything2image/assets/image/car_image.jpg
anything2image/assets/image/dog_image.jpg
anything2image/assets/image/room.png
anything2image/assets/thermal/030419.jpg
anything2image/assets/thermal/030444.jpg
anything2image/assets/wav/bird_audio.wav
anything2image/assets/wav/car_audio.wav
anything2image/assets/wav/cat.wav
anything2image/assets/wav/cattle.wav
anything2image/assets/wav/dog_audio.wav
anything2image/assets/wav/fire_engine.wav
anything2image/assets/wav/goat.wav
anything2image/assets/wav/motorcycle.wav
anything2image/assets/wav/plane.wav
anything2image/assets/wav/rain.wav
anything2image/assets/wav/train.wav
anything2image/assets/wav/wave.wav
anything2image/imagebind/__init__.py
anything2image/imagebind/data.py
anything2image/imagebind/bpe/bpe_simple_vocab_16e6.txt.gz
anything2image/imagebind/models/__init__.py
anything2image/imagebind/models/helpers.py
anything2image/imagebind/models/imagebind_model.py
anything2image/imagebind/models/multimodal_preprocessors.py
anything2image/imagebind/models/transformer.py
anything2image-1.1.4.dist-info/METADATA
anything2image-1.1.4.dist-info/WHEEL
anything2image-1.1.4.dist-info/top_level.txt
anything2image-1.1.4.dist-info/RECORD
