Metadata-Version: 2.1
Name: anything2image
Version: 1.1.4
Requires-Dist: diffusers
Requires-Dist: timm (==0.6.7)
Requires-Dist: ftfy
Requires-Dist: regex
Requires-Dist: einops
Requires-Dist: fvcore
Requires-Dist: decord (==0.6.0)
Requires-Dist: soundfile
Requires-Dist: transformers
Requires-Dist: gradio
Requires-Dist: fire
Requires-Dist: pytorchvideo
Requires-Dist: accelerate
